snmpsim/__init__.py
snmpsim/confdir.py
snmpsim/controller.py
snmpsim/daemon.py
snmpsim/datafile.py
snmpsim/endpoints.py
snmpsim/error.py
snmpsim/log.py
snmpsim/utils.py
snmpsim/variation.py
snmpsim/commands/__init__.py
snmpsim/commands/cmd2rec.py
snmpsim/commands/mib2rec.py
snmpsim/commands/pcap2rec.py
snmpsim/commands/rec2rec.py
snmpsim/commands/responder.py
snmpsim/commands/responder_lite.py
snmpsim/data/README.txt
snmpsim/data/public.snmprec
snmpsim/data/1.3.6.1.6.1.1.0/127.0.0.1.snmprec
snmpsim/data/1.3.6.1.6.1.1.0/README-v2c.txt
snmpsim/data/1.3.6.1.6.1.1.0/README-v3.txt
snmpsim/data/foreignformats/README.txt
snmpsim/data/foreignformats/linux.snmpwalk
snmpsim/data/foreignformats/winxp1.snmpwalk
snmpsim/data/foreignformats/winxp2.sapwalk
snmpsim/data/mib2dev/host-resources-mib.snmprec
snmpsim/data/mib2dev/ip-mib.snmprec
snmpsim/data/mib2dev/tcp-mib.snmprec
snmpsim/data/mib2dev/udp-mib.snmprec
snmpsim/data/public/1.3.6.1.2.1.100.1.13.0.snmprec
snmpsim/data/public/README-v2c.txt
snmpsim/data/public/README-v3.txt
snmpsim/data/public/1.3.6.1.2.1.100.1.2.0/README-v2c.txt
snmpsim/data/public/1.3.6.1.2.1.100.1.2.0/README-v3.txt
snmpsim/data/public/1.3.6.1.2.1.100.1.2.0/__1.snmprec
snmpsim/data/public/1.3.6.1.6.1.1.0/127.0.0.1.snmprec
snmpsim/data/public/1.3.6.1.6.1.1.0/README-v2c.txt
snmpsim/data/public/1.3.6.1.6.1.1.0/README-v3.txt
snmpsim/data/recorded/eaton-9PX-partial-walk.snmprec
snmpsim/data/recorded/linksys-system.snmprec
snmpsim/data/recorded/linux-full-walk.snmprec
snmpsim/data/recorded/solaris-system.snmprec
snmpsim/data/recorded/udp-endpoint-table-walk.snmprec
snmpsim/data/recorded/winxp-full-walk.snmprec
snmpsim/data/variation/README.txt
snmpsim/data/variation/delay.snmprec
snmpsim/data/variation/error.snmprec
snmpsim/data/variation/multiplex.snmprec
snmpsim/data/variation/notification.snmprec
snmpsim/data/variation/sql.snmprec
snmpsim/data/variation/subprocess.snmprec
snmpsim/data/variation/virtualtable.snmprec
snmpsim/data/variation/writecache.snmprec
snmpsim-1.2.0.dist-info/METADATA
snmpsim-1.2.0.dist-info/WHEEL
snmpsim-1.2.0.dist-info/entry_points.txt
snmpsim-1.2.0.dist-info/licenses/LICENSE.txt
snmpsim-1.2.0.dist-info/RECORD
