Metadata-Version: 2.4
Name: snmpsim
Version: 1.2.0
Summary: SNMP Simulator is a tool that acts as multitude of SNMP Agents built into real physical devices, from SNMP Manager's point of view. Simulator builds and uses a database of physical devices' SNMP footprints to respond like their original counterparts do.
Project-URL: Repository, https://github.com/lextudio/snmpsim
Author-email: Ilya Etingof <etingof@gmail.com>, "LeXtudio Inc." <support@lextudio.com>
License: BSD-2-Clause
License-File: LICENSE.txt
Classifier: Development Status :: 5 - Production/Stable
Classifier: Environment :: Console
Classifier: Intended Audience :: Developers
Classifier: Intended Audience :: Education
Classifier: Intended Audience :: Information Technology
Classifier: Intended Audience :: System Administrators
Classifier: Intended Audience :: Telecommunications Industry
Classifier: License :: OSI Approved :: BSD License
Classifier: Natural Language :: English
Classifier: Operating System :: OS Independent
Classifier: Topic :: Communications
Classifier: Topic :: System :: Monitoring
Classifier: Topic :: System :: Networking :: Monitoring
Requires-Python: <4.0,>=3.10
Requires-Dist: pysnmp<8.0.0,>=7.1.0
Provides-Extra: dev
Requires-Dist: black==23.1.0; extra == 'dev'
Requires-Dist: bump2version>=1.0.1; extra == 'dev'
Requires-Dist: codecov<3.0.0; extra == 'dev'
Requires-Dist: codecov>=2.1.12; extra == 'dev'
Requires-Dist: cryptography<44.0.0; extra == 'dev'
Requires-Dist: cryptography>=43.0.0; extra == 'dev'
Requires-Dist: doc8<2.0.0; extra == 'dev'
Requires-Dist: doc8>=1.1.1; extra == 'dev'
Requires-Dist: furo<2025.0.0; extra == 'dev'
Requires-Dist: furo>=2024.1.1; extra == 'dev'
Requires-Dist: pre-commit==2.21.0; extra == 'dev'
Requires-Dist: pysmi<2.0.0; extra == 'dev'
Requires-Dist: pysmi>=1.5.0; extra == 'dev'
Requires-Dist: pytest-asyncio<0.22.0; extra == 'dev'
Requires-Dist: pytest-asyncio>=0.21.1; extra == 'dev'
Requires-Dist: pytest-codecov<1.0.0; extra == 'dev'
Requires-Dist: pytest-codecov>=0.4.0; extra == 'dev'
Requires-Dist: pytest<8.0.0; extra == 'dev'
Requires-Dist: pytest>=7.2.0; extra == 'dev'
Requires-Dist: sphinx-copybutton<0.6.0; extra == 'dev'
Requires-Dist: sphinx-copybutton>=0.5.2; extra == 'dev'
Requires-Dist: sphinx-notfound-page<2.0.0; extra == 'dev'
Requires-Dist: sphinx-notfound-page>=1.0.0; extra == 'dev'
Requires-Dist: sphinx-sitemap-lextudio<3.0.0; extra == 'dev'
Requires-Dist: sphinx-sitemap-lextudio>=2.5.2; extra == 'dev'
Requires-Dist: sphinx<8.0.0; extra == 'dev'
Requires-Dist: sphinx>=7.0.0; extra == 'dev'
